{
  "userId":1,
  "time":"2020-01-08",
  "content":"亲爱的召唤师：\n\n我们将在1月10日10点左右更换每周免费英雄啦。\n\n下面为大家介绍下新一周的免费英雄——\n\n每周免费英雄：\n\n冰霜女巫 丽桑卓\t解脱者 塞拉斯\t时光守护者 基兰\t机械先驱 维克托\t刀锋舞者 艾瑞莉娅\t荒漠屠夫 雷克顿\t放逐之刃 锐雯\t瘟疫之源 图奇\n死亡颂唱者\t魔蛇之拥\t暮光星灵\t爆破鬼才\t武器大师\t牧魂人\t龙血武姬\t复仇之矛\n卡尔萨斯\t卡西奥佩娅\t佐伊\t吉格斯\t贾克斯\t约里克\t希瓦娜\t卡莉丝塔\n \t \t \t \t \t \t \t \n麦林炮手 崔丝塔娜\t翠神 艾翁\t离群之刺 阿卡丽\t刀锋之影 泰隆\t唤潮鲛姬 娜美\t唤潮鲛姬 娜美\t风暴之怒 迦娜\n英勇投弹手\t北地之怒\t山隐之焰\t潮汐海灵\t永恒梦魇\t深海泰坦\t曙光女神\n库奇\t瑟庄妮\t奥恩\t菲兹\t魔腾\t诺提勒斯\t蕾欧娜\n永久免费：\n\n迅捷斥候 提莫\n寒冰射手 艾希\n符文法师 瑞兹\n德玛西亚之力 盖伦\n迅捷斥候\n寒冰射手\n符文法师\n德玛西亚之力\n提莫\n艾希\n瑞兹\n盖伦\n什么是每周免费英雄呢?就算你没有买英雄，在游戏中也有数个免费英雄可以使用。免费英雄会在每周五轮换，这样大家不用 花钱也能体验到不同英雄带来的乐趣。为了提升游戏体验，并让玩家体验到更多的游戏内容，每周轮换的周免英雄数量调整为游戏整体英雄数量的10%(四舍五入)，因此周免英雄数量增加到了15个。\n另外，在中国的服务器中，我们额外增加了四个永久免费使用的英雄——迅捷斥候 提莫、寒冰射手 艾希、德玛西亚之力 盖伦和符文法师 瑞兹 。主要目的也是便于那些刚刚打完新手实战训练营的玩家能够至少有一个自己会用的英雄。",
  "tag":1,
  "title":"1月10日免费英雄更新公告",
  "link":" ",
  "gameId":1
}