[
  {
    "number":0,
    "codeName":"iG.Sword",
    "realName":"Sword",
    "position":1,
    "teamId":1,
    "avatar":"https://blz.nosdn.127.net/2/Esports/2019GTC/players/iG.Sword.png"
  },
  {
    "number":1,
    "codeName":"iG.TheDing",
    "realName":"TheDing",
    "position":2,
    "teamId":1,
    "avatar":"https://blz.nosdn.127.net/2/Esports/2019GTC/players/iG.Wang.png"
  },
  {
    "number":2,
    "codeName":"iG.Syf",
    "realName":"Syf",
    "position":3,
    "teamId":1,
    "avatar":"https://blz.nosdn.127.net/2/Esports/2019GTC/players/iG.Syf.png"
  },
  {
    "number":3,
    "codeName":"iG.XC",
    "realName":"XC",
    "position":2,
    "teamId":1,
    "avatar":"https://blz.nosdn.127.net/2/Esports/2019GTC/players/iG.XC.png"
  },
  {
    "number":4,
    "codeName":"iG.XiaoYao",
    "realName":"XiaoYao",
    "position":2,
    "teamId":1,
    "avatar":"https://blz.nosdn.127.net/2/Esports/2019GTC/players/iG.XiaoYao.png"
  }
]